fluxllm/__init__.py
fluxllm/client_utils/__init__.py
fluxllm/client_utils/cache.py
fluxllm/client_utils/progress.py
fluxllm/clients/__init__.py
fluxllm/clients/base.py
fluxllm/clients/openai.py
fluxllm-0.2.0.dist-info/licenses/LICENSE
fluxllm-0.2.0.dist-info/METADATA
fluxllm-0.2.0.dist-info/WHEEL
fluxllm-0.2.0.dist-info/top_level.txt
fluxllm-0.2.0.dist-info/RECORD
