Metadata-Version: 2.4
Name: fluxllm
Version: 0.2.0
Summary: A blazing-fast gateway for asynchronous, high-concurrency LLM requests (OpenAI, Claude, etc.).
Author-email: Lei Zhang <jameszhang2880@gmail.com>
License: MIT
Classifier: Programming Language :: Python :: 3
Classifier: License :: OSI Approved :: MIT License
Classifier: Operating System :: OS Independent
Requires-Python: >=3.9
License-File: LICENSE
Requires-Dist: openai
Requires-Dist: rich
Requires-Dist: aiolimiter
Provides-Extra: test
Requires-Dist: pytest; extra == "test"
Requires-Dist: pytest-asyncio; extra == "test"
Requires-Dist: fastapi; extra == "test"
Requires-Dist: uvicorn; extra == "test"
Dynamic: license-file
